rapids_logger/VERSION
rapids_logger/__init__.py
rapids_logger/_version.py
rapids_logger/load.py
rapids_logger/include/rapids_logger/log_levels.h
rapids_logger/include/rapids_logger/logger.hpp
rapids_logger/lib64/librapids_logger.so
rapids_logger/lib64/cmake/rapids_logger/create_logger_macros.cmake
rapids_logger/lib64/cmake/rapids_logger/logger_macros.hpp.in
rapids_logger/lib64/cmake/rapids_logger/rapids_logger-config-version.cmake
rapids_logger/lib64/cmake/rapids_logger/rapids_logger-config.cmake
rapids_logger/lib64/cmake/rapids_logger/rapids_logger-targets-release.cmake
rapids_logger/lib64/cmake/rapids_logger/rapids_logger-targets.cmake
rapids_logger-0.2.3.dist-info/METADATA
rapids_logger-0.2.3.dist-info/WHEEL
rapids_logger-0.2.3.dist-info/entry_points.txt
rapids_logger-0.2.3.dist-info/RECORD
rapids_logger-0.2.3.dist-info/licenses/LICENSE
