Metadata-Version: 2.1
Name: rapids-logger
Version: 0.2.3
Summary: Logging framework for RAPIDS built around spdlog
Author: NVIDIA Corporation
License: Apache 2.0
Classifier: Intended Audience :: Developers
Classifier: Topic :: Database
Classifier: Topic :: Scientific/Engineering
Classifier: License :: OSI Approved :: Apache Software License
Classifier: Programming Language :: C++
Project-URL: Homepage, https://github.com/rapidsai/rapids-logger
Requires-Python: >=3.10
